qingcloud_hpc/HpcApiConnection.py
qingcloud_hpc/__init__.py
qingcloud_hpc/build.py
qingcloud_hpc/build_request.py
qingcloud_hpc/config.py
qingcloud_hpc/constant.py
qingcloud_hpc/error.py
qingcloud_hpc/request.py
qingcloud_hpc/unpack.py
qingcloud_hpc/build/__init__.py
qingcloud_hpc/build/lib/__init__.py
qingcloud_hpc/build/lib/cli_utils/__init__.py
qingcloud_hpc/build/lib/cli_utils/helper.py
qingcloud_hpc/build/lib/cmd/__init__.py
qingcloud_hpc/build/lib/cmd/hpc.py
qingcloud_hpc/build/lib/sdk_api/HpcApiConnection.py
qingcloud_hpc/build/lib/sdk_api/__init__.py
qingcloud_hpc/build/lib/sdk_api/build_sdk.py
qingcloud_hpc/build/lib/sdk_api/constants.py
qingcloud_hpc/build/lib/sdk_api/hpc.py
qingcloud_hpc/cli_utils/__init__.py
qingcloud_hpc/cli_utils/helper.py
qingcloud_hpc/cmd/__init__.py
qingcloud_hpc/cmd/hpc.py
qingcloud_hpc/dist/__init__.py
qingcloud_hpc/sdk_api/HpcApiConnection.py
qingcloud_hpc/sdk_api/__init__.py
qingcloud_hpc/sdk_api/build_sdk.py
qingcloud_hpc/sdk_api/constants.py
qingcloud_hpc/sdk_api/hpc.py
qingcloud_hpc/sdk_api/tests/__init__.py
qingcloud_hpc/sdk_api/tests/test_hpc.py
qingcloud_hpc-0.0.1.dist-info/METADATA
qingcloud_hpc-0.0.1.dist-info/WHEEL
qingcloud_hpc-0.0.1.dist-info/top_level.txt
qingcloud_hpc-0.0.1.dist-info/RECORD
